LICENSE.txt
MANIFEST.in
README.md
requirements.txt
setup.cfg
setup.py
livingbio_warlock.egg-info/PKG-INFO
livingbio_warlock.egg-info/SOURCES.txt
livingbio_warlock.egg-info/dependency_links.txt
livingbio_warlock.egg-info/requires.txt
livingbio_warlock.egg-info/top_level.txt
test/test_core.py
warlock/__init__.py
warlock/core.py
warlock/exceptions.py
warlock/model.py