Metadata-Version: 1.0
Name: livingbio-warlock
Version: 1.3.0
Summary: Python object model built on JSON schema and JSON patch.
Home-page: http://github.com/bcwaldon/warlock
Author: Brian Waldon
Author-email: bcwaldon@gmail.com
License: UNKNOWN
Platform: UNKNOWN
